smart_mrag/__init__.py
smart_mrag/core.py
smart_mrag/utils.py
smart_mrag/version.py
smart_mrag-0.1.5.dist-info/licenses/LICENSE
smart_mrag-0.1.5.dist-info/METADATA
smart_mrag-0.1.5.dist-info/WHEEL
smart_mrag-0.1.5.dist-info/top_level.txt
smart_mrag-0.1.5.dist-info/RECORD
