Metadata-Version: 2.4
Name: smart_mrag
Version: 0.1.5
Summary: A smart Multi-modal RAG (Retrieval Augmented Generation) library for processing PDFs with various language models
Home-page: https://github.com/adity-narvekar/smart_mrag
Author: Aditya Narvekar
Author-email: Aditya Narvekar <Aditya.narvekar@gmail.com>
License: MIT
Project-URL: Homepage, https://github.com/yourusername/smart_mrag
Project-URL: Bug Tracker, https://github.com/yourusername/smart_mrag/issues
Classifier: Development Status :: 3 - Alpha
Classifier: Intended Audience :: Developers
Classifier: License :: OSI Approved :: MIT License
Classifier: Operating System :: OS Independent
Classifier: Programming Language :: Python :: 3
Classifier: Programming Language :: Python :: 3.8
Classifier: Programming Language :: Python :: 3.9
Classifier: Programming Language :: Python :: 3.10
Requires-Python: >=3.8
License-File: LICENSE
Requires-Dist: langchain>=0.3.14
Requires-Dist: langchain-community>=0.3.14
Requires-Dist: langchain-openai>=0.3.0
Requires-Dist: langchain-core>=0.3.29
Requires-Dist: faiss-cpu>=1.9.0
Requires-Dist: pymupdf>=1.25.1
Requires-Dist: Pillow>=10.4.0
Requires-Dist: pypdf>=5.1.0
Requires-Dist: python-dotenv>=1.0.1
Requires-Dist: openai>=1.59.6
Requires-Dist: numpy>=1.26.2
Requires-Dist: pydantic>=2.0.0
Requires-Dist: tqdm>=4.64.0
Dynamic: author
Dynamic: home-page
Dynamic: license-file
Dynamic: requires-python
